Workbook
Name \__: #REF!
Name \0: #N/A
Name \a: #N/A
Name \AA: #REF!
Name \b: #N/A
Name \c: #N/A
Name \CC: #REF!
Name \d: #N/A
Name \e: #N/A
Name \f: #N/A
Name \g: #N/A
Name \h: #N/A
Name \i: #N/A
Name \j: #N/A
Name \k: #N/A
Name \KWS123: #N/A
Name \l: #REF!
Name \m: #N/A
Name \n: #N/A
Name \o: #REF!
Name \OO: #REF!
Name \P: #REF!
Name \P: #REF!
Name \q: #N/A
Name \R: #REF!
Name \s: #N/A
Name \t: #N/A
Name \U: #REF!
Name \V: #REF!
Name \X: #REF!
Name \Y: #REF!
Name \z: #N/A
Name _: #REF!
Name _: #REF!
Name ___: #REF!
Name _________________NS1: #REF!
Name ________________NS1: #REF!
Name _______________NS1: #REF!
Name ______________NS1: #REF!
Name _____________NS1: #REF!
Name ____________a1: #REF!
Name ____________NS1: #REF!
Name ___________a1: #REF!
Name ___________No1: #REF!
Name ___________No2: #REF!
Name ___________No3: #REF!
Name ___________NS1: #REF!
Name ___________sdb2: #REF!
Name __________a1: #REF!
Name __________dep123: #REF!
Name __________No1: #REF!
Name __________No2: #REF!
Name __________No3: #REF!
Name __________NS1: #REF!
Name __________sdb2: #REF!
Name _________a1: #REF!
Name _________a100: #REF!
Name _________dep123: #REF!
Name _________ETC01: #REF!
Name _________No1: #REF!

Sheet Budget
B3: MOFARREH MARZOUQ AL-HARBI & PARTNERS CO. LTD.
B5: Baseline Budget Rev. 0 EFFECTIVE BUDGET LEVLE ( 4 )
V6: *Key Legend
C7: Project name: WO# | W7: Pay Item level | Z7: Project Duration:
C8: Project No.: WO# | W8: Activity Level | Z8: Notice to proceed date:
C9: Client: | W9: Resource Level | Z9: Currency: SAR
AE10: 1e-19
A11: Item Type | B11: BOQ Item No. | C11: BOQ Description | D11: Unit | E11: Original BOQ | J11: Effective BOQ | V11: Cost Code | W11: Resources | AE11: Remaining Budget Breakdown Category
E12: Original QTY | F12: Original Selling | H12: Original Budget | J12: QTY | O12: Effective Selling | Q12: Effective Budget | W12: Res./Act. | X12: Res. Category | Y12: Res./Act. Unit | Z12: Resource Rate (SR) | AA12: Resource Productivity (MH/UNIT) | AB12: Res./Act. Budget (SR) | AC12: Res./Act. QTY | AD12: Total Cost
F13: Selling Rate | G13: Contract Amount | H13: Budget Rate | I13: Budget Amount | J13: Revised QTY | K13: Effective QTY | L13: Executed QTY upto Dec-25 | M13: Remaining QTY upto Dec-25 | N13: Remaining % | O13: Effective Selling Rate | P13: Effective Contract Amount | Q13: Effective Budget Rate | R13: ETC | S13: AC upto Dec-25 | T13: Revised Budget Amount | U13: Actual Rate | AE13: Machinery | AF13: Material | AG13: Manpower | AH13: SC | AI13: Total
C15: Total Budget | E15: 1 | G15: =G16+G35 -> 2.3377608e+08 | I15: =I16+I35 -> 1.5820276e+08 | P15: =P16+P35 -> 2.3377608e+08 | R15: =R16+R35 -> 1.5820276e+08 | S15: =S16+S35 -> 0 | T15: =T16+T35 -> 1.5820276e+08
C16: Indirect Budget | E16: 1 | G16: =SUM(G17:G34) -> 0 | I16: =SUM(I17:I34) -> 37202527 | P16: =SUM(P17:P34) -> 0 | R16: =SUM(R17:R34) -> 37202527 | S16: =SUM(S17:S34) -> 0 | T16: =SUM(T17:T34) -> 37202527
B17: IND01 | C17: Indirect Labour Cost | D17: Ea | E17: 1 | H17: 19627660 | I17: =H17*E17 -> 19627660 | J17: =E17 -> 1 | K17: =E17 -> 1 | M17: =K17-L17 -> 1 | Q17: 19627660 | R17: =M17*Q17 -> 19627660 | T17: =S17+R17 -> 19627660
B18: IND02 | C18: Staff Cars | D18: Ea | E18: 1 | H18: 2192647 | I18: =H18*E18 -> 2192647 | J18: =E18 -> 1 | K18: =E18 -> 1 | M18: =K18-L18 -> 1 | Q18: 2192647 | R18: =M18*Q18 -> 2192647 | T18: =S18+R18 -> 2192647
B19: IND03 | C19: Fuel for Staff Cars | D19: Ea | E19: 1 | H19: 593611.5 | I19: =H19*E19 -> 593611.5 | J19: =E19 -> 1 | K19: =E19 -> 1 | M19: =K19-L19 -> 1 | Q19: 593611.5 | R19: =M19*Q19 -> 593611.5 | T19: =S19+R19 -> 593611.5
B20: IND04 | C20: Indirect Equipment Cost | D20: Ea | E20: 1 | H20: 2736630 | I20: =H20*E20 -> 2736630 | J20: =E20 -> 1 | K20: =E20 -> 1 | M20: =K20-L20 -> 1 | Q20: 2736630 | R20: =M20*Q20 -> 2736630 | T20: =S20+R20 -> 2736630
B21: IND05 | C21: Fuel for Indirect Equip. | D21: Ea | E21: 1 | H21: 1262384.5 | I21: =H21*E21 -> 1262384.5 | J21: =E21 -> 1 | K21: =E21 -> 1 | M21: =K21-L21 -> 1 | O21: =F21 -> 0 | P21: =K21*O21 -> 0 | Q21: 1262384.5 | R21: =M21*Q21 -> 1262384.5 | T21: =S21+R21 -> 1262384.5
B22: IND06 | C22: Camp Cost (Food and Accommodation) | D22: Ea | E22: 1 | H22: 4174002 | I22: =H22*E22 -> 4174002 | J22: =E22 -> 1 | K22: =E22 -> 1 | M22: =K22-L22 -> 1 | Q22: 4174002 | R22: =M22*Q22 -> 4174002 | T22: =S22+R22 -> 4174002
B23: IND07 | C23: Mobilization | D23: Ea | E23: 1 | H23: 546000 | I23: =H23*E23 -> 546000 | J23: =E23 -> 1 | K23: =E23 -> 1 | M23: =K23-L23 -> 1 | Q23: 546000 | R23: =M23*Q23 -> 546000 | T23: =S23+R23 -> 546000
B24: IND08 | C24: Demobilization | D24: Ea | E24: 1 | H24: 54600 | I24: =H24*E24 -> 54600 | J24: =E24 -> 1 | K24: =E24 -> 1 | M24: =K24-L24 -> 1 | Q24: 54600 | R24: =M24*Q24 -> 54600 | T24: =S24+R24 -> 54600
B25: IND09 | C25: General Tools | D25: Ea | E25: 1 | H25: 108100 | I25: =H25*E25 -> 108100 | J25: =E25 -> 1 | K25: =E25 -> 1 | M25: =K25-L25 -> 1 | Q25: 108100 | R25: =M25*Q25 -> 108100 | T25: =S25+R25 -> 108100
B26: IND10 | C26: Project Running Cost | D26: Ea | E26: 1 | H26: 519000 | I26: =H26*E26 -> 519000 | J26: =E26 -> 1 | K26: =E26 -> 1 | M26: =K26-L26 -> 1 | Q26: 519000 | R26: =M26*Q26 -> 519000 | T26: =S26+R26 -> 519000
B27: IND11 | C27: Waste Management | D27: Ea | E27: 1 | H27: 893600 | I27: =H27*E27 -> 893600 | J27: =E27 -> 1 | K27: =E27 -> 1 | M27: =K27-L27 -> 1 | Q27: 893600 | R27: =M27*Q27 -> 893600 | T27: =S27+R27 -> 893600
B28: IND12 | C28: Safety, Medical & Traffic Control | D28: Ea | E28: 1 | H28: 514091 | I28: =H28*E28 -> 514091 | J28: =E28 -> 1 | K28: =E28 -> 1 | M28: =K28-L28 -> 1 | Q28: 514091 | R28: =M28*Q28 -> 514091 | T28: =S28+R28 -> 514091
B29: IND13 | C29: Lab Testing & Project Services | D29: Ea | E29: 1 | H29: 288000 | I29: =H29*E29 -> 288000 | J29: =E29 -> 1 | K29: =E29 -> 1 | M29: =K29-L29 -> 1 | Q29: 288000 | R29: =M29*Q29 -> 288000 | T29: =S29+R29 -> 288000
B30: IND14 | C30: Survey Expenses | D30: Ea | E30: 1 | H30: 50000 | I30: =H30*E30 -> 50000 | J30: =E30 -> 1 | K30: =E30 -> 1 | M30: =K30-L30 -> 1 | Q30: 50000 | R30: =M30*Q30 -> 50000 | T30: =S30+R30 -> 50000
B31: IND15 | C31: Security Expenses | D31: Ea | E31: 1 | H31: 720000 | I31: =H31*E31 -> 720000 | J31: =E31 -> 1 | K31: =E31 -> 1 | M31: =K31-L31 -> 1 | Q31: 720000 | R31: =M31*Q31 -> 720000 | T31: =S31+R31 -> 720000
B32: IND16 | C32: Design Services | D32: Ea | E32: 1 | H32: 0 | I32: =H32*E32 -> 0 | J32: =E32 -> 1 | K32: =E32 -> 1 | M32: =K32-L32 -> 1 | Q32: 0 | R32: =M32*Q32 -> 0 | T32: =S32+R32 -> 0
B33: IND17 | C33: Warrantee Period Maintenance Cost | D33: Ea | E33: 1 | H33: 584440.19 | I33: =H33*E33 -> 584440.19 | J33: =E33 -> 1 | K33: =E33 -> 1 | M33: =K33-L33 -> 1 | Q33: 584440.19 | R33: =M33*Q33 -> 584440.19 | T33: =S33+R33 -> 584440.19
B34: IND18 | C34: Program Overhead | D34: Ea | E34: 1 | H34: 2337760.8 | I34: =H34*E34 -> 2337760.8 | J34: =E34 -> 1 | K34: =E34 -> 1 | M34: =K34-L34 -> 1 | Q34: 2337760.8 | R34: =M34*Q34 -> 2337760.8 | T34: =S34+R34 -> 2337760.8
C35: Direct Budget | G35: =+SUMIF($AK:$AK,"5",G:G) -> 2.3377608e+08 | I35: =+SUMIF($AK:$AK,"5",I:I) -> 1.2100023e+08 | P35: =+SUMIF($AK:$AK,"5",P:P) -> 2.3377608e+08 | R35: =+SUMIF($AK:$AK,"5",R:R) -> 1.2100023e+08 | S35: =+SUMIF($AK:$AK,"5",S:S) -> 0 | T35: =+SUMIF($AK:$AK,"5",T:T) -> 1.2100023e+08 | AD35: =+SUMIF($AK:$AK,"5",AD:AD) -> 1.2100023e+08 | AE35: =SUMIF($AK:$AK,5,AE:AE) -> 219500 | AF35: =SUMIF($AK:$AK,5,AF:AF) -> 219500 | AG35: =SUMIF($AK:$AK,5,AG:AG) -> 219500 | AH35: =SUMIF($AK:$AK,5,AH:AH) -> 219500 | AI35: =SUMIF($AK:$AK,5,AI:AI) -> 878000
A37: General items | B37: 1 | C37: Preparing, installing and setting up site offices | D37: sum | E37: 0.1 | F37: 617230 | G37: =F37*E37 -> 61723 | H37: =AB37 -> 925000 | I37: =H37*E37 -> 92500 | J37: =E37 -> 0.1 | K37: =J37 -> 0.1 | M37: =K37-L37 -> 0.1 | N37: =IFERROR(M37/K37,0) -> 1 | O37: =F37 -> 617230 | P37: =K37*O37 -> 61723 | Q37: =AB37 -> 925000 | R37: =M37*Q37 -> 92500 | T37: =S37+R37 -> 92500 | AB37: =AD37/AC37 -> 925000 | AC37: =M37+$AE$10 -> 0.1 | AD37: =AD38 -> 92500 | AE37: =AE38 -> 0 | AF37: =AF38 -> 0 | AG37: =AG38 -> 0 | AH37: =AH38 -> 0 | AI37: =SUM(AE37:AH37) -> 0 | AK37: 5 | AO37: Original Pay item
J38: =J37 -> 0.1 | K38: =K37 -> 0.1 | M38: =K38-L38 -> 0.1 | W38: Setting up site offices (Remining Works) | Y38: LS | Z38: =AD38/AC38 -> 925000 | AB38: =AD38/AC38 -> 925000 | AC38: =M38+$AE$10 -> 0.1 | AD38: =SUM(AD39:AD45) -> 92500 | AE38: =SUMIFS($AD$37:$AD$12971,$V$37:$V$12971,$V38,$X$37:$X$12971,AE$13) -> 0 | AF38: =SUMIFS($AD$37:$AD$12971,$V$37:$V$12971,$V38,$X$37:$X$12971,AF$13) -> 0 | AG38: =SUMIFS($AD$37:$AD$12971,$V$37:$V$12971,$V38,$X$37:$X$12971,AG$13) -> 0 | AH38: =SUMIFS($AD$37:$AD$12971,$V$37:$V$12971,$V38,$X$37:$X$12971,AH$13) -> 0 | AI38: =SUM(AE38:AH38) -> 0
W39: Supply and applying Electric connections | X39: SC | Y39: LS | Z39: =VLOOKUP(W39,Sheet2!$B:$D,3,FALSE) -> 25000 | AA39: =1/10 -> 0.1 | AB39: =AD39/AC38 -> 250000 | AC39: =AC38/AA39 -> 1 | AD39: =AC39*Z39 -> 25000
W40: Supply and applying Mechnical connections | X40: SC | Y40: LS | Z40: =VLOOKUP(W40,Sheet2!$B:$D,3,FALSE) -> 35000 | AA40: 0.1 | AB40: =AD40/AC38 -> 350000 | AC40: =AC38/AA40 -> 1 | AD40: =AC40*Z40 -> 35000
W41: Supply and Apply Plants with the Soil Mix | X41: SC | Y41: LS | Z41: =VLOOKUP(W41,Sheet2!$B:$D,3,FALSE) -> 10000 | AA41: 0.1 | AB41: =AD41/AC38 -> 100000 | AC41: =AC38/AA41 -> 1 | AD41: =AC41*Z41 -> 10000
W42: Supply AC Unit | X42: Material | Y42: LS | Z42: =VLOOKUP(W42,Sheet2!$B:$D,3,FALSE) -> 13000 | AA42: 0.1 | AB42: =AD42/AC38 -> 130000 | AC42: =AC38/AA42 -> 1 | AD42: =AC42*Z42 -> 13000
W43: Supply cabines Doors | X43: Material | Y43: LS | Z43: =VLOOKUP(W43,Sheet2!$B:$D,3,FALSE) -> 6500 | AA43: 0.1 | AB43: =AD43/AC38 -> 65000 | AC43: =AC38/AA43 -> 1 | AD43: =AC43*Z43 -> 6500
W44: Skilled Labor | X44: Manpower | Y44: HR | Z44: =VLOOKUP(W44,Sheet2!$B:$D,3,FALSE) -> 17 | AA44: 0.001 | AB44: =AD44/AC38 -> 17000 | AC44: =AC38/AA44 -> 100 | AD44: =AC44*Z44 -> 1700
W45: Unskilled Labour | X45: Manpower | Y45: HR | Z45: =VLOOKUP(W45,Sheet2!$B:$D,3,FALSE) -> 13 | AA45: 0.001 | AB45: =AD45/AC38 -> 13000 | AC45: =AC38/AA45 -> 100 | AD45: =AC45*Z45 -> 1300
A46: General items | B46: 2 | C46: Maintaining and maintaining site offices | D46: days | E46: 294 | F46: 2374 | G46: =F46*E46 -> 697956 | H46: =AB46 -> 153.06122 | I46: =H46*E46 -> 45000 | J46: =E46 -> 294 | K46: =J46 -> 294 | M46: =K46-L46 -> 294 | N46: =IFERROR(M46/K46,0) -> 1 | O46: =F46 -> 2374 | P46: =K46*O46 -> 697956 | Q46: =AB46 -> 153.06122 | R46: =M46*Q46 -> 45000 | T46: =S46+R46 -> 45000 | AB46: =AD46/AC46 -> 153.06122 | AC46: =M46+$AE$10 -> 294 | AD46: =AD47 -> 45000 | AE46: =AE47 -> 0 | AF46: =AF47 -> 0 | AG46: =AG47 -> 0 | AH46: =AH47 -> 0 | AI46: =SUM(AE46:AH46) -> 0 | AK46: 5 | AO46: Original Pay item
J47: =J46 -> 294 | K47: =K46 -> 294 | M47: =K47-L47 -> 294 | W47: Maintenance of Offices (Remining Works) | Y47: LS | Z47: =AD47/AC47 -> 153.06122 | AB47: =AD47/AC47 -> 153.06122 | AC47: =M47+$AE$10 -> 294 | AD47: =SUM(AD48:AD50) -> 45000 | AE47: =SUMIFS($AD$37:$AD$12971,$V$37:$V$12971,$V47,$X$37:$X$12971,AE$13) -> 0 | AF47: =SUMIFS($AD$37:$AD$12971,$V$37:$V$12971,$V47,$X$37:$X$12971,AF$13) -> 0 | AG47: =SUMIFS($AD$37:$AD$12971,$V$37:$V$12971,$V47,$X$37:$X$12971,AG$13) -> 0 | AH47: =SUMIFS($AD$37:$AD$12971,$V$37:$V$12971,$V47,$X$37:$X$12971,AH$13) -> 0 | AI47: =SUM(AE47:AH47) -> 0
W48: Maintaining the Offices Floor and slabs | X48: SC | Y48: LS | Z48: =VLOOKUP(W48,Sheet2!$B:$D,3,FALSE) -> 25000 | AA48: 294 | AB48: =AD48/AC47 -> 85.034014 | AC48: =AC47/AA48 -> 1 | AD48: =AC48*Z48 -> 25000
W49: Maintaining the Offices Wall Paints | X49: SC | Y49: LS | Z49: =VLOOKUP(W49,Sheet2!$B:$D,3,FALSE) -> 11000 | AA49: 294 | AB49: =AD49/AC47 -> 37.414966 | AC49: =AC47/AA49 -> 1 | AD49: =AC49*Z49 -> 11000
W50: Supply and apply furnitures | X50: SC | Y50: LS | Z50: =VLOOKUP(W50,Sheet2!$B:$D,3,FALSE) -> 9000 | AA50: 294 | AB50: =AD50/AC47 -> 30.612245 | AC50: =AC47/AA50 -> 1 | AD50: =AC50*Z50 -> 9000
A51: General items | B51: 3 | C51: Soil testing equipment | D51: sum | E51: 0.3 | F51: 12588 | G51: =F51*E51 -> 3776.4 | H51: =AB51 -> 94000 | I51: =H51*E51 -> 28200 | J51: =E51 -> 0.3 | K51: =J51 -> 0.3 | M51: =K51-L51 -> 0.3 | N51: =IFERROR(M51/K51,0) -> 1 | O51: =F51 -> 12588 | P51: =K51*O51 -> 3776.4 | Q51: =AB51 -> 94000 | R51: =M51*Q51 -> 28200 | T51: =S51+R51 -> 28200 | AB51: =AD51/AC51 -> 94000 | AC51: =M51+$AE$10 -> 0.3 | AD51: =AD52 -> 28200 | AE51: =AE52 -> 0 | AF51: =AF52 -> 0 | AG51: =AG52 -> 0 | AH51: =AH52 -> 0 | AI51: =SUM(AE51:AH51) -> 0 | AK51: 5 | AO51: Original Pay item
J52: =J51 -> 0.3 | K52: =K51 -> 0.3 | M52: =K52-L52 -> 0.3 | W52: Soil testing equipment | Y52: LS | Z52: =AD52/AC52 -> 94000 | AB52: =AD52/AC52 -> 94000 | AC52: =M52+$AE$10 -> 0.3 | AD52: =SUM(AD53) -> 28200 | AE52: =SUMIFS($AD$37:$AD$12971,$V$37:$V$12971,$V52,$X$37:$X$12971,AE$13) -> 0 | AF52: =SUMIFS($AD$37:$AD$12971,$V$37:$V$12971,$V52,$X$37:$X$12971,AF$13) -> 0 | AG52: =SUMIFS($AD$37:$AD$12971,$V$37:$V$12971,$V52,$X$37:$X$12971,AG$13) -> 0 | AH52: =SUMIFS($AD$37:$AD$12971,$V$37:$V$12971,$V52,$X$37:$X$12971,AH$13) -> 0 | AI52: =SUM(AE52:AH52) -> 0
W53: Soil testing equipment | X53: SC | Y53: LS | Z53: =VLOOKUP(W53,Sheet2!$B:$D,3,FALSE) -> 94000 | AA53: 1 | AB53: =AD53/AC52 -> 94000 | AC53: =AC52/AA53 -> 0.3 | AD53: =AC53*Z53 -> 28200
A54: General items | B54: 4 | C54: Asphalt testing equipment | D54: sum | E54: 0.5 | F54: 8812 | G54: =F54*E54 -> 4406 | H54: =AB54 -> 112800 | I54: =H54*E54 -> 56400 | J54: =E54 -> 0.5 | K54: =J54 -> 0.5 | M54: =K54-L54 -> 0.5 | N54: =IFERROR(M54/K54,0) -> 1 | O54: =F54 -> 8812 | P54: =K54*O54 -> 4406 | Q54: =AB54 -> 112800 | R54: =M54*Q54 -> 56400 | T54: =S54+R54 -> 56400 | AB54: =AD54/AC54 -> 112800 | AC54: =M54+$AE$10 -> 0.5 | AD54: =AD55 -> 56400 | AE54: =AE55 -> 0 | AF54: =AF55 -> 0 | AG54: =AG55 -> 0 | AH54: =AH55 -> 0 | AI54: =SUM(AE54:AH54) -> 0 | AK54: 5 | AO54: Original Pay item
J55: =J54 -> 0.5 | K55: =K54 -> 0.5 | M55: =K55-L55 -> 0.5 | W55: Asphalt testing equipment | Y55: LS | Z55: =AD55/AC55 -> 112800 | AB55: =AD55/AC55 -> 112800 | AC55: =M55+$AE$10 -> 0.5 | AD55: =SUM(AD56) -> 56400 | AE55: =SUMIFS($AD$37:$AD$12971,$V$37:$V$12971,$V55,$X$37:$X$12971,AE$13) -> 0 | AF55: =SUMIFS($AD$37:$AD$12971,$V$37:$V$12971,$V55,$X$37:$X$12971,AF$13) -> 0 | AG55: =SUMIFS($AD$37:$AD$12971,$V$37:$V$12971,$V55,$X$37:$X$12971,AG$13) -> 0 | AH55: =SUMIFS($AD$37:$AD$12971,$V$37:$V$12971,$V55,$X$37:$X$12971,AH$13) -> 0 | AI55: =SUM(AE55:AH55) -> 0
W56: Asphalt testing equipment | X56: SC | Y56: LS | Z56: =VLOOKUP(W56,Sheet2!$B:$D,3,FALSE) -> 112800 | AA56: 1 | AB56: =AD56/AC55 -> 112800 | AC56: =AC55/AA56 -> 0.5 | AD56: =AC56*Z56 -> 56400
A57: General items | B57: 5 | C57: Concrete testing equipment | D57: sum | E57: 0.3 | F57: 10070 | G57: =F57*E57 -> 3021 | H57: =AB57 -> 94000 | I57: =H57*E57 -> 28200 | J57: =E57 -> 0.3 | K57: =J57 -> 0.3 | M57: =K57-L57 -> 0.3 | N57: =IFERROR(M57/K57,0) -> 1 | O57: =F57 -> 10070 | P57: =K57*O57 -> 3021 | Q57: =AB57 -> 94000 | R57: =M57*Q57 -> 28200 | T57: =S57+R57 -> 28200 | AB57: =AD57/AC57 -> 94000 | AC57: =M57+$AE$10 -> 0.3 | AD57: =AD58 -> 28200 | AE57: =AE58 -> 0 | AF57: =AF58 -> 0 | AG57: =AG58 -> 0 | AH57: =AH58 -> 0 | AI57: =SUM(AE57:AH57) -> 0 | AK57: 5 | AO57: Original Pay item
J58: =J57 -> 0.3 | K58: =K57 -> 0.3 | M58: =K58-L58 -> 0.3 | W58: Concrete testing equipment | Y58: LS | Z58: =AD58/AC58 -> 94000 | AB58: =AD58/AC58 -> 94000 | AC58: =M58+$AE$10 -> 0.3 | AD58: =SUM(AD59) -> 28200 | AE58: =SUMIFS($AD$37:$AD$12971,$V$37:$V$12971,$V58,$X$37:$X$12971,AE$13) -> 0 | AF58: =SUMIFS($AD$37:$AD$12971,$V$37:$V$12971,$V58,$X$37:$X$12971,AF$13) -> 0 | AG58: =SUMIFS($AD$37:$AD$12971,$V$37:$V$12971,$V58,$X$37:$X$12971,AG$13) -> 0 | AH58: =SUMIFS($AD$37:$AD$12971,$V$37:$V$12971,$V58,$X$37:$X$12971,AH$13) -> 0 | AI58: =SUM(AE58:AH58) -> 0
W59: Concrete testing equipment | X59: SC | Y59: LS | Z59: =VLOOKUP(W59,Sheet2!$B:$D,3,FALSE) -> 94000 | AA59: 1 | AB59: =AD59/AC58 -> 94000 | AC59: =AC58/AA59 -> 0.3 | AD59: =AC59*Z59 -> 28200
A60: General items | B60: 6 | C60: Providing four (4) laboratory workers for the duration of the project | D60: sum | E60: 0.3 | F60: 1727084 | G60: =F60*E60 -> 518125.2 | H60: =AB60 -> 2000000 | I60: =H60*E60 -> 600000 | J60: =E60 -> 0.3 | K60: =J60 -> 0.3 | M60: =K60-L60 -> 0.3 | N60: =IFERROR(M60/K60,0) -> 1 | O60: =F60 -> 1727084 | P60: =K60*O60 -> 518125.2 | Q60: =AB60 -> 2000000 | R60: =M60*Q60 -> 600000 | T60: =S60+R60 -> 600000 | AB60: =AD60/AC60 -> 2000000 | AC60: =M60+$AE$10 -> 0.3 | AD60: =AD61 -> 600000 | AE60: =AE61 -> 0 | AF60: =AF61 -> 0 | AG60: =AG61 -> 0 | AH60: =AH61 -> 0 | AI60: =SUM(AE60:AH60) -> 0 | AK60: 5 | AO60: Original Pay item
J61: =J60 -> 0.3 | K61: =K60 -> 0.3 | M61: =K61-L61 -> 0.3 | W61: Lab Technicians | Y61: LS | Z61: =AD61/AC61 -> 2000000 | AB61: =AD61/AC61 -> 2000000 | AC61: =M61+$AE$10 -> 0.3 | AD61: =SUM(AD62:AD62) -> 600000 | AE61: =SUMIFS($AD$37:$AD$12971,$V$37:$V$12971,$V61,$X$37:$X$12971,AE$13) -> 0 | AF61: =SUMIFS($AD$37:$AD$12971,$V$37:$V$12971,$V61,$X$37:$X$12971,AF$13) -> 0 | AG61: =SUMIFS($AD$37:$AD$12971,$V$37:$V$12971,$V61,$X$37:$X$12971,AG$13) -> 0 | AH61: =SUMIFS($AD$37:$AD$12971,$V$37:$V$12971,$V61,$X$37:$X$12971,AH$13) -> 0 | AI61: =SUM(AE61:AH61) -> 0
W62: Hiring Two Technicians with Vechicle | X62: SC | Y62: Months | Z62: =VLOOKUP(W62,Sheet2!$B:$D,3,FALSE) -> 25000 | AA62: =0.3/24 -> 0.0125 | AB62: =AD62/AC61 -> 2000000 | AC62: =AC61/AA62 -> 24 | AD62: =AC62*Z62 -> 600000
A63: General items | B63: 7 | C63: Computers and surveying devices | D63: sum | E63: 0.3 | F63: 314702 | G63: =F63*E63 -> 94410.6 | H63: =AB63 -> 100000 | I63: =H63*E63 -> 30000 | J63: =E63 -> 0.3 | K63: =J63 -> 0.3 | M63: =K63-L63 -> 0.3 | N63: =IFERROR(M63/K63,0) -> 1 | O63: =F63 -> 314702 | P63: =K63*O63 -> 94410.6 | Q63: =AB63 -> 100000 | R63: =M63*Q63 -> 30000 | T63: =S63+R63 -> 30000 | AB63: =AD63/AC63 -> 100000 | AC63: =M63+$AE$10 -> 0.3 | AD63: =AD64 -> 30000 | AE63: =AE64 -> 0 | AF63: =AF64 -> 0 | AG63: =AG64 -> 0 | AH63: =AH64 -> 0 | AI63: =SUM(AE63:AH63) -> 0 | AK63: 5 | AO63: Original Pay item
J64: =J63 -> 0.3 | K64: =K63 -> 0.3 | M64: =K64-L64 -> 0.3 | W64: Computers and surveying devices | Y64: LS | Z64: =AD64/AC64 -> 100000 | AB64: =AD64/AC64 -> 100000 | AC64: =M64+$AE$10 -> 0.3 | AD64: =SUM(AD65:AD65) -> 30000 | AE64: =SUMIFS($AD$37:$AD$12971,$V$37:$V$12971,$V64,$X$37:$X$12971,AE$13) -> 0 | AF64: =SUMIFS($AD$37:$AD$12971,$V$37:$V$12971,$V64,$X$37:$X$12971,AF$13) -> 0 | AG64: =SUMIFS($AD$37:$AD$12971,$V$37:$V$12971,$V64,$X$37:$X$12971,AG$13) -> 0 | AH64: =SUMIFS($AD$37:$AD$12971,$V$37:$V$12971,$V64,$X$37:$X$12971,AH$13) -> 0 | AI64: =SUM(AE64:AH64) -> 0
W65: Computers and surveying devices | X65: SC | Y65: LS | Z65: =VLOOKUP(W65,Sheet2!$B:$D,3,FALSE) -> 100000 | AA65: 1 | AB65: =AD65/AC64 -> 100000 | AC65: =AC64/AA65 -> 0.3 | AD65: =AC65*Z65 -> 30000
C66: Earthworks - Roads
A67: Roads | B67: 8 | C67: Cleaning and removing weeds, trees and roots | D67: m² | E67: 4547.23 | F67: 4 | G67: =F67*E67 -> 18188.92 | H67: =AB67 -> 0.46125359 | I67: =H67*E67 -> 2097.4262 | J67: =E67 -> 4547.23 | K67: =J67 -> 4547.23 | M67: =K67-L67 -> 4547.23 | N67: =IFERROR(M67/K67,0) -> 1 | O67: =F67 -> 4 | P67: =K67*O67 -> 18188.92 | Q67: =AB67 -> 0.46125359 | R67: =M67*Q67 -> 2097.4262 | T67: =S67+R67 -> 2097.4262 | AB67: =AD67/AC67 -> 0.46125359 | AC67: =M67+$AE$10 -> 4547.23 | AD67: =AD68 -> 2097.4262 | AE67: =AE68 -> 0 | AF67: =AF68 -> 0 | AG67: =AG68 -> 0 | AH67: =AH68 -> 0 | AI67: =SUM(AE67:AH67) -> 0 | AK67: 5 | AO67: Original Pay item
J68: =J67 -> 4547.23 | K68: =K67 -> 4547.23 | M68: =K68-L68 -> 4547.23 | W68: Site Clearance with disposal | Y68: M² | Z68: =AD68/AC68 -> 0.46125359 | AB68: =AD68/AC68 -> 0.46125359 | AC68: =M68+$AE$10 -> 4547.23 | AD68: =SUM(AD69:AD75) -> 2097.4262 | AE68: =SUMIFS($AD$37:$AD$12971,$V$37:$V$12971,$V68,$X$37:$X$12971,AE$13) -> 0 | AF68: =SUMIFS($AD$37:$AD$12971,$V$37:$V$12971,$V68,$X$37:$X$12971,AF$13) -> 0 | AG68: =SUMIFS($AD$37:$AD$12971,$V$37:$V$12971,$V68,$X$37:$X$12971,AG$13) -> 0 | AH68: =SUMIFS($AD$37:$AD$12971,$V$37:$V$12971,$V68,$X$37:$X$12971,AH$13) -> 0 | AI68: =SUM(AE68:AH68) -> 0
W69: Grader | X69: Machinery | Y69: HR | Z69: =VLOOKUP(W69,Sheet2!$B:$D,3,FALSE) -> 90.4 | AA69: 600 | AB69: =AD69/AC68 -> 0.15066667 | AC69: =AC68/AA69 -> 7.5787167 | AD69: =AC69*Z69 -> 685.11599
W70: Fuel | X70: Material | Y70: LTR | Z70: =VLOOKUP(W70,Sheet2!$B:$D,3,FALSE) -> 1.76 | AA70: =AA69/21 -> 28.571429 | AB70: =AD70/AC68 -> 0.0616 | AC70: =AC68/AA70 -> 159.15305 | AD70: =AC70*Z70 -> 280.10937
W71: Wheel Loader | X71: Machinery | Y71: HR | Z71: =VLOOKUP(W71,Sheet2!$B:$D,3,FALSE) -> 65.6 | AA71: =AA73*3 -> 1224 | AB71: =AD71/AC68 -> 0.053594771 | AC71: =AC68/AA71 -> 3.7150572 | AD71: =AC71*Z71 -> 243.70775
W72: Fuel | X72: Material | Y72: LTR | Z72: =VLOOKUP(W72,Sheet2!$B:$D,3,FALSE) -> 1.76 | AA72: =AA71/9 -> 136 | AB72: =AD72/AC68 -> 0.012941176 | AC72: =AC68/AA72 -> 33.435515 | AD72: =AC72*Z72 -> 58.846506 | AJ72: 122 | AK72: =AJ72/0.1 -> 1220
W73: Dump Truck 16 m³ | X73: Machinery | Y73: HR | Z73: =VLOOKUP(W73,Sheet2!$B:$D,3,FALSE) -> 48 | AA73: =((16*0.85)*3)/0.1 -> 408 | AB73: =AD73/AC68 -> 0.11764706 | AC73: =AC68/AA73 -> 11.145172 | AD73: =AC73*Z73 -> 534.96824
W74: Fuel | X74: Material | Y74: LTR | Z74: =VLOOKUP(W74,Sheet2!$B:$D,3,FALSE) -> 1.76 | AA74: =AA73/10 -> 40.8 | AB74: =AD74/AC68 -> 0.043137255 | AC74: =AC68/AA74 -> 111.45172 | AD74: =AC74*Z74 -> 196.15502
W75: Unskilled Labour | X75: Manpower | Y75: HR | Z75: =VLOOKUP(W75,Sheet2!$B:$D,3,FALSE) -> 13 | AA75: =AA69 -> 600 | AB75: =AD75/AC68 -> 0.021666667 | AC75: =AC68/AA75 -> 7.5787167 | AD75: =AC75*Z75 -> 98.523317
A76: Roads | B76: 9 | C76: Precast Curbstone type (K1-D) | D76: m | E76: 9616 | F76: 79 | G76: =F76*E76 -> 759664 | H76: =AB76 -> 45 | I76: =H76*E76 -> 432720 | J76: =E76 -> 9616 | K76: =J76 -> 9616 | M76: =K76-L76 -> 9616 | N76: =IFERROR(M76/K76,0) -> 1 | O76: =F76 -> 79 | P76: =K76*O76 -> 759664 | Q76: =AB76 -> 45 | R76: =M76*Q76 -> 432720 | T76: =S76+R76 -> 432720 | AB76: =AD76/AC76 -> 45 | AC76: =M76+$AE$10 -> 9616 | AD76: =AD77 -> 432720 | AE76: =AE77 -> 0 | AF76: =AF77 -> 0 | AG76: =AG77 -> 0 | AH76: =AH77 -> 0 | AI76: =SUM(AE76:AH76) -> 0 | AK76: 5 | AO76: Original Pay item
J77: =J76 -> 9616 | K77: =K76 -> 9616 | M77: =K77-L77 -> 9616 | W77: Supply & Install Curbstone | Y77: M | Z77: =AD77/AC77 -> 45 | AB77: =AD77/AC77 -> 45 | AC77: =M77+$AE$10 -> 9616 | AD77: =SUM(AD78:AD79) -> 432720 | AE77: =SUMIFS($AD$37:$AD$12971,$V$37:$V$12971,$V77,$X$37:$X$12971,AE$13) -> 0 | AF77: =SUMIFS($AD$37:$AD$12971,$V$37:$V$12971,$V77,$X$37:$X$12971,AF$13) -> 0 | AG77: =SUMIFS($AD$37:$AD$12971,$V$37:$V$12971,$V77,$X$37:$X$12971,AG$13) -> 0 | AH77: =SUMIFS($AD$37:$AD$12971,$V$37:$V$12971,$V77,$X$37:$X$12971,AH$13) -> 0 | AI77: =SUM(AE77:AH77) -> 0
W78: Curbstone Supply | X78: Material | Y78: LM | Z78: =VLOOKUP(W78,Sheet2!$B:$D,3,FALSE) -> 18 | AA78: 1 | AB78: =AD78/AC77 -> 18 | AC78: =AC77/AA78 -> 9616 | AD78: =AC78*Z78 -> 173088
W79: Curbstone Installation | X79: SC | Y79: LM | Z79: =VLOOKUP(W79,Sheet2!$B:$D,3,FALSE) -> 27 | AA79: 1 | AB79: =AD79/AC77 -> 27 | AC79: =AC77/AA79 -> 9616 | AD79: =AC79*Z79 -> 259632
A80: local road | C80: Bituminous construction - Local Roads
A81: local road | B81: 1 | C81: Bituminous foundation layer (MC 1) | D81: m² | E81: 142.28 | F81: 5 | G81: =F81*E81 -> 711.4 | H81: =AB81 -> 3.45 | I81: =H81*E81 -> 490.866 | J81: =E81 -> 142.28 | K81: =J81 -> 142.28 | M81: =K81-L81 -> 142.28 | N81: =IFERROR(M81/K81,0) -> 1 | O81: =F81 -> 5 | P81: =K81*O81 -> 711.4 | Q81: =AB81 -> 3.45 | R81: =M81*Q81 -> 490.866 | T81: =S81+R81 -> 490.866 | AB81: =AD81/AC81 -> 3.45 | AC81: =M81+$AE$10 -> 142.28 | AD81: =AD82 -> 490.866 | AE81: =AE82 -> 0 | AF81: =AF82 -> 0 | AG81: =AG82 -> 0 | AH81: =AH82 -> 0 | AI81: =SUM(AE81:AH81) -> 0 | AK81: 5 | AO81: Original Pay item
J82: =J81 -> 142.28 | K82: =K81 -> 142.28 | M82: =K82-L82 -> 142.28 | W82: MC1 Works | Y82: M² | Z82: =AD82/AC82 -> 3.45 | AB82: =AD82/AC82 -> 3.45 | AC82: =M82+$AE$10 -> 142.28 | AD82: =SUM(AD83:AD84) -> 490.866 | AE82: =SUMIFS($AD$37:$AD$12971,$V$37:$V$12971,$V82,$X$37:$X$12971,AE$13) -> 0 | AF82: =SUMIFS($AD$37:$AD$12971,$V$37:$V$12971,$V82,$X$37:$X$12971,AF$13) -> 0 | AG82: =SUMIFS($AD$37:$AD$12971,$V$37:$V$12971,$V82,$X$37:$X$12971,AG$13) -> 0 | AH82: =SUMIFS($AD$37:$AD$12971,$V$37:$V$12971,$V82,$X$37:$X$12971,AH$13) -> 0 | AI82: =SUM(AE82:AH82) -> 0
W83: Supply MC1 | X83: Material | Y83: Ton | Z83: =VLOOKUP(W83,Sheet2!$B:$D,3,FALSE) -> 2450 | AA83: 1000 | AB83: =AD83/AC82 -> 2.45 | AC83: =AC82/AA83 -> 0.14228 | AD83: =AC83*Z83 -> 348.586
W84: Spray MC1 | X84: SC | Y84: M² | Z84: =VLOOKUP(W84,Sheet2!$B:$D,3,FALSE) -> 1 | AA84: 1 | AB84: =AD84/AC82 -> 1 | AC84: =AC82/AA84 -> 142.28 | AD84: =AC84*Z84 -> 142.28
A85: local road | B85: 2 | C85: Bituminous base layer (Grade 1 - Class A) with a thickness of 70 mm after compaction | D85: m³ | E85: 46.3824 | F85: 1007 | G85: =F85*E85 -> 46707.077 | H85: =AB85 -> 585.6 | I85: =H85*E85 -> 27161.533 | J85: =E85 -> 46.3824 | K85: =J85 -> 46.3824 | M85: =K85-L85 -> 46.3824 | N85: =IFERROR(M85/K85,0) -> 1 | O85: =F85 -> 1007 | P85: =K85*O85 -> 46707.077 | Q85: =AB85 -> 585.6 | R85: =M85*Q85 -> 27161.533 | T85: =S85+R85 -> 27161.533 | AB85: =AD85/AC85 -> 585.6 | AC85: =M85+$AE$10 -> 46.3824 | AD85: =AD86 -> 27161.533 | AE85: =AE86 -> 0 | AF85: =AF86 -> 0 | AG85: =AG86 -> 0 | AH85: =AH86 -> 0 | AI85: =SUM(AE85:AH85) -> 0 | AK85: 5 | AO85: Original Pay item
J86: =J85 -> 46.3824 | K86: =K85 -> 46.3824 | M86: =K86-L86 -> 46.3824 | W86: Binder Course Works 70 mm | Y86: M³ | Z86: =AD86/AC86 -> 585.6 | AB86: =AD86/AC86 -> 585.6 | AC86: =M86+$AE$10 -> 46.3824 | AD86: =SUM(AD87:AD89) -> 27161.533 | AE86: =SUMIFS($AD$37:$AD$12971,$V$37:$V$12971,$V86,$X$37:$X$12971,AE$13) -> 0 | AF86: =SUMIFS($AD$37:$AD$12971,$V$37:$V$12971,$V86,$X$37:$X$12971,AF$13) -> 0 | AG86: =SUMIFS($AD$37:$AD$12971,$V$37:$V$12971,$V86,$X$37:$X$12971,AG$13) -> 0 | AH86: =SUMIFS($AD$37:$AD$12971,$V$37:$V$12971,$V86,$X$37:$X$12971,AH$13) -> 0 | AI86: =SUM(AE86:AH86) -> 0
W87: Supply Asphalt Binder Course | X87: Material | Y87: Ton | Z87: =VLOOKUP(W87,Sheet2!$B:$D,3,FALSE) -> 200 | AA87: =1/2.4 -> 0.41666667 | AB87: =AD87/AC86 -> 480 | AC87: =AC86/AA87 -> 111.31776 | AD87: =AC87*Z87 -> 22263.552
W88: Asphalt Transportation 0-60 KM | X88: SC | Y88: Ton | Z88: =VLOOKUP(W88,Sheet2!$B:$D,3,FALSE) -> 19 | AA88: =AA87 -> 0.41666667 | AB88: =AD88/AC86 -> 45.6 | AC88: =AC86/AA88 -> 111.31776 | AD88: =AC88*Z88 -> 2115.0374
W89: Apply Asphalt Binder Course 7 CM | X89: SC | Y89: M² | Z89: =VLOOKUP(W89,Sheet2!$B:$D,3,FALSE) -> 4.2 | AA89: =1*0.07 -> 0.07 | AB89: =AD89/AC86 -> 60 | AC89: =AC86/AA89 -> 662.60571 | AD89: =AC89*Z89 -> 2782.944
A90: local road | B90: 3 | C90: The upper surface layer of bituminous concrete with a thickness of 50 mm after compaction (Grade 1 - Class A), including the adhesive layer (R.C). | D90: m³ | E90: 72.55 | F90: 1007 | G90: =F90*E90 -> 73057.85 | H90: =AB90 -> 802.68889 | I90: =H90*E90 -> 58235.079 | J90: =E90 -> 72.55 | K90: =J90 -> 72.55 | M90: =K90-L90 -> 72.55 | N90: =IFERROR(M90/K90,0) -> 1 | O90: =F90 -> 1007 | P90: =K90*O90 -> 73057.85 | Q90: =AB90 -> 802.68889 | R90: =M90*Q90 -> 58235.079 | T90: =S90+R90 -> 58235.079 | AB90: =AD90/AC90 -> 802.68889 | AC90: =M90+$AE$10 -> 72.55 | AD90: =AD91 -> 58235.079 | AE90: =AE91 -> 0 | AF90: =AF91 -> 0 | AG90: =AG91 -> 0 | AH90: =AH91 -> 0 | AI90: =SUM(AE90:AH90) -> 0 | AK90: 5 | AO90: Original Pay item
J91: =J90 -> 72.55 | K91: =K90 -> 72.55 | M91: =K91-L91 -> 72.55 | W91: Wearing Course Works 50 mm | Y91: M³ | Z91: =AD91/AC91 -> 802.68889 | AB91: =AD91/AC91 -> 802.68889 | AC91: =M91+$AE$10 -> 72.55 | AD91: =SUM(AD92:AD97) -> 58235.079 | AE91: =SUMIFS($AD$37:$AD$12971,$V$37:$V$12971,$V91,$X$37:$X$12971,AE$13) -> 0 | AF91: =SUMIFS($AD$37:$AD$12971,$V$37:$V$12971,$V91,$X$37:$X$12971,AF$13) -> 0 | AG91: =SUMIFS($AD$37:$AD$12971,$V$37:$V$12971,$V91,$X$37:$X$12971,AG$13) -> 0 | AH91: =SUMIFS($AD$37:$AD$12971,$V$37:$V$12971,$V91,$X$37:$X$12971,AH$13) -> 0 | AI91: =SUM(AE91:AH91) -> 0
W92: Supply RC2 | X92: Material | Y92: Ton | Z92: =VLOOKUP(W92,Sheet2!$B:$D,3,FALSE) -> 2550 | AA92: =900*0.05 -> 45 | AB92: =AD92/AC91 -> 56.666667 | AC92: =AC91/AA92 -> 1.6122222 | AD92: =AC92*Z92 -> 4111.1667
W93: Asphalt Transportation 0-60 KM | X93: SC | Y93: Ton | Z93: =VLOOKUP(W93,Sheet2!$B:$D,3,FALSE) -> 19 | AA93: =AA92 -> 45 | AB93: =AD93/AC91 -> 0.42222222 | AC93: =AC91/AA93 -> 1.6122222 | AD93: =AC93*Z93 -> 30.632222
W94: Spray RC2 | X94: SC | Y94: M² | Z94: =VLOOKUP(W94,Sheet2!$B:$D,3,FALSE) -> 1 | AA94: =1*0.05 -> 0.05 | AB94: =AD94/AC91 -> 20 | AC94: =AC91/AA94 -> 1451 | AD94: =AC94*Z94 -> 1451
W95: Supply bituminous concrete 50 mm | X95: Material | Y95: Ton | Z95: =VLOOKUP(W95,Sheet2!$B:$D,3,FALSE) -> 250 | AA95: =1/2.4 -> 0.41666667 | AB95: =AD95/AC91 -> 600 | AC95: =AC91/AA95 -> 174.12 | AD95: =AC95*Z95 -> 43530
W96: Asphalt Transportation 0-60 KM | X96: SC | Y96: Ton | Z96: =VLOOKUP(W96,Sheet2!$B:$D,3,FALSE) -> 19 | AA96: =AA95 -> 0.41666667 | AB96: =AD96/AC91 -> 45.6 | AC96: =AC91/AA96 -> 174.12 | AD96: =AC96*Z96 -> 3308.28
W97: Apply Asphalt Wearing Course 3-5 CM | X97: SC | Y97: M² | Z97: =VLOOKUP(W97,Sheet2!$B:$D,3,FALSE) -> 4 | AA97: =1*0.05 -> 0.05 | AB97: =AD97/AC91 -> 80 | AC97: =AC91/AA97 -> 1451 | AD97: =AC97*Z97 -> 5804
A98: local road | C98: Curbstone
A99: local road | C99: Precast cold storage works include pouring foundation concrete on site, (concrete base and hunching), cement mortar, reinforcement, excavation, backfilling, compaction, painting, disposal of waste, and completing the work as required in accordance with the standards of the competent authorities, specifications and design plans. | AO99: Original Pay item
A100: local road | B100: 4 | C100: Precast Curbstone type (K1-D) | D100: m | E100: 237.75 | F100: 72 | G100: =F100*E100 -> 17118 | H100: =AB100 -> 45 | I100: =H100*E100 -> 10698.75 | J100: =E100 -> 237.75 | K100: =J100 -> 237.75 | M100: =K100-L100 -> 237.75 | N100: =IFERROR(M100/K100,0) -> 1 | O100: =F100 -> 72 | P100: =K100*O100 -> 17118 | Q100: =AB100 -> 45 | R100: =M100*Q100 -> 10698.75 | T100: =S100+R100 -> 10698.75 | AB100: =AD100/AC100 -> 45 | AC100: =M100+$AE$10 -> 237.75 | AD100: =AD101 -> 10698.75 | AE100: =AE101 -> 0 | AF100: =AF101 -> 0 | AG100: =AG101 -> 0 | AH100: =AH101 -> 0 | AI100: =SUM(AE100:AH100) -> 0 | AK100: 5 | AO100: Original Pay item
J101: =J100 -> 237.75 | K101: =K100 -> 237.75 | M101: =K101-L101 -> 237.75 | W101: Supply & Install Curbstone | Y101: M | Z101: =AD101/AC101 -> 45 | AB101: =AD101/AC101 -> 45 | AC101: =M101+$AE$10 -> 237.75 | AD101: =SUM(AD102:AD103) -> 10698.75 | AE101: =SUMIFS($AD$37:$AD$12971,$V$37:$V$12971,$V101,$X$37:$X$12971,AE$13) -> 0 | AF101: =SUMIFS($AD$37:$AD$12971,$V$37:$V$12971,$V101,$X$37:$X$12971,AF$13) -> 0 | AG101: =SUMIFS($AD$37:$AD$12971,$V$37:$V$12971,$V101,$X$37:$X$12971,AG$13) -> 0 | AH101: =SUMIFS($AD$37:$AD$12971,$V$37:$V$12971,$V101,$X$37:$X$12971,AH$13) -> 0 | AI101: =SUM(AE101:AH101) -> 0
W102: Curbstone Supply | X102: Material | Y102: LM | Z102: =VLOOKUP(W102,Sheet2!$B:$D,3,FALSE) -> 18 | AA102: 1 | AB102: =AD102/AC101 -> 18 | AC102: =AC101/AA102 -> 237.75 | AD102: =AC102*Z102 -> 4279.5
W103: Curbstone Installation | X103: SC | Y103: LM | Z103: =VLOOKUP(W103,Sheet2!$B:$D,3,FALSE) -> 27 | AA103: 1 | AB103: =AD103/AC101 -> 27 | AC103: =AC101/AA103 -> 237.75 | AD103: =AC103*Z103 -> 6419.25
C104: Manholes and pipework accessories-Telecom 7
C105: Ducts
...

Sheet Sheet2
B3: Resources | C3: UOM | D3: Rate | E3: Type
B4: Fuel | C4: Ltre | D4: 1.76
B5: Unskilled Labour | C5: HR | D5: 13
B6: Skilled Labor | C6: HR | D6: 17
B7: Bulldozer CAT D9 | C7: HR | D7: 132.304
B8: Bulldozer CAT D8 | C8: HR | D8: 111.568
B9: Bulldozer CAT D4 | C9: HR | D9: 105
B10: Wheel Excavator 20T With Bucket/Hock | C10: HR | D10: 68
B11: Excavator with Bucket 20T | C11: HR | D11: 56
B12: Excavator with Hydraulic Hammer 20T | C12: HR | D12: 58.4
B13: Excavator with Bucket 50T | C13: HR | D13: 131.2
B14: Excavator with Hydraulic Hammer 50T | C14: HR | D14: 150.4
B15: Excavator 75T with Bucket | C15: HR | D15: 236
... B127: Non-woven Geotextile Installation | C127: M² | D127: 0.9
B128: Orange warning Mesh | C128: M² | D128: =30/50 -> 0.6
B131: 125 mm solid HDPE Pipe DR 11 | C131: M | D131: 35
B132: 160 mm solid HDPE Pipe DR 11 | C132: M | D132: 39
B133: 200 mm solid HDPE Pipe DR 11 | C133: M | D133: 50
B134: 225 mm solid HDPE Pipe DR 11 | C134: M | D134: 75
B135: 250 mm solid HDPE Pipe DR 11 | C135: M | D135: 95
B136: 280 mm solid HDPE Pipe DR 11 | C136: M | D136: 110
B137: 315 mm solid HDPE Pipe DR 11 | C137: M | D137: 145
B138: 355 mm solid HDPE Pipe DR 11 | C138: M | D138: 190
B139: 400 mm solid HDPE Pipe DR 11 | C139: M | D139: 229.9
B140: 500 mm solid HDPE Pipe DR 11 | C140: M | D140: 345
B141: 560 mm solid HDPE Pipe DR 11 | C141: M | D141: 510
B142: 630 mm solid HDPE Pipe DR 11 | C142: M | D142: 610
... B149: 250 mm HDPE Pipe Installation | C149: M | D149: 30
B150: 280 mm HDPE Pipe Installation | C150: M | D150: 33 | H150: 160 mm HDPE Fittings & Accessories | I150: M | J150: 25
B151: 315 mm HDPE Pipe Installation | C151: M | D151: 38 | H151: 200 mm HDPE Fittings & Accessories | I151: M | J151: 30
B152: 355 mm HDPE Pipe Installation | C152: M | D152: 44 | H152: 315 mm HDPE Fittings & Accessories | I152: M | J152: 130
B153: 400 mm HDPE Pipe Installation | C153: M | D153: 50 | H153: 400 mm HDPE Fittings & Accessories | I153: M | J153: 180
B154: 500 mm HDPE Pipe Installation | C154: M | D154: 55 | H154: 630 mm HDPE Fittings & Accessories | I154: M | J154: 250
B155: 560 mm HDPE Pipe Installation | C155: M | D155: 60
B156: 630 mm HDPE Pipe Installation | C156: M | D156: 60
B157: 710 mm HDPE Pipe Installation | C157: M | D157: 120
B159: Supply Elbow 11.5°, diameter 125mm | C159: Ea | D159: 205
B160: Supply Elbow 45°, diameter 125mm | C160: Ea | D160: 215
B161: Supply Elbow 90°, diameter 125mm | C161: Ea | D161: 227.5
B162: Supply Elbow 11.5°, diameter 160mm | C162: Ea | D162: 224.5
B163: Supply Elbow 45°, diameter 160mm | C163: Ea | D163: 229
B164: Supply Elbow 45°, diameter 200 mm | C164: Ea | D164: 260
B165: Supply Elbow 11.25°, diameter 250 mm | C165: Ea | D165: 300
B166: Supply Elbow 22.5°, diameter 250 mm | C166: Ea | D166: 312
B167: Supply Elbow 45°, diameter 250 mm | C167: Ea | D167: 335.4
... B235: Supply Gate Valve 200 mm | C235: Ea | D235: 1268
B236: Fitting and Accessories 200 | C236: Ea | D236: =0.1*D235 -> 126.8
B237: Installation Valve 200mm | C237: Ea | D237: 150
B238: Supply Gate Valve 225 mm | C238: Ea | D238: 1552
B239: Fitting and Accessories 225 | C239: Ea | D239: =0.1*D238 -> 155.2
B240: Installation Valve 225mm | C240: Ea | D240: 150
B241: Supply Gate Valve 250 MM | C241: Ea | D241: 1700
B242: Supply Air Valve 250 MM | C242: Ea | D242: 1870
B243: Fitting and Accessories 250 | C243: Ea | D243: =0.1*D241 -> 170
B244: Installation Valve 250mm | C244: Ea | D244: 150
B245: Supply Gate Valve 280 MM | C245: Ea | D245: 1870
B246: Supply Air Valve 280 MM | C246: Ea | D246: 2160
B247: Fitting and Accessories 280 | C247: Ea | D247: 170
B248: Installation Valve 280mm | C248: Ea | D248: 200
B249: Supply Gate Valve 315 MM | C249: Ea | D249: 2200
B250: Supply Air Valve 315 MM | C250: Ea | D250: 2825
B251: Fitting and Accessories 315 | C251: Ea | D251: =0.1*D249 -> 220
B252: Installation Valve 315mm | C252: Ea | D252: 200
B253: Butterfly Valve for 355mm | C253: Ea | D253: 4550
B254: Fitting and Accessories 355 | C254: Ea | D254: =0.1*D253 -> 455
B255: Installation Valve 355mm | C255: Ea | D255: 200
B256: Supply Butterfly Valve 500 MM | C256: Ea | D256: 7210
B257: Supply Air Valve 500 MM | C257: Ea | D257: 7750
B258: Fitting and Accessories 500 | C258: Ea | D258: 721
B259: Installation Valve 500mm | C259: Ea | D259: 1500
B260: Supply Butterfly Valve 560 MM | C260: Ea | D260: 8250
B261: Fitting and Accessories 560 | C261: Ea | D261: =0.1*D260 -> 825
B262: Installation Valve 560mm | C262: Ea | D262: 250
B263: Supply Butterfly Valve 630 MM | C263: Ea | D263: 9750
B264: Supply Air Valve 630 MM | C264: Ea | D264: 10150
B265: Fitting and Accessories 630 | C265: Ea | D265: 975
B266: Installation Valve 630mm | C266: Ea | D266: 1500
B267: Supply Butterfly Valve 710 MM | C267: Ea | D267: 10250
B268: Fitting and Accessories 710 | C268: Ea | D268: =0.1*D267 -> 1025
B269: Installation Valve 710mm | C269: Ea | D269: 400
B270: Supply & Install 3-outlet fire nozzle | C270: LS | D270: 8531
B271: Supply & apply Flow Meter 125 mm | C271: Ea | D271: 11757.36
B272: Supply & apply Flow Meter 280 mm | C272: Ea | D272: 13616.99
B273: Supply & apply Flow Meter 355 mm | C273: Ea | D273: 16328.61
B274: Supply & apply Flow Meter 500 mm | C274: Ea | D274: 26328.61
B275: Supply & apply Flow Meter 560 mm | C275: Ea | D275: 35250
B276: Supply & apply Flow Meter 710 mm | C276: Ea | D276: 48500
B277: Supply & apply Flow Meter 800 mm | C277: Ea | D277: 175250
B278: Supply & apply KW250 elec water pump 295 l/s | C278: Ea | D278: 630093.75
B279: Supply & apply elec fire water pump 64 l/s | C279: Ea | D279: 193875
B280: Supply & apply Diesel fire water pump 64 l/s | C280: Ea | D280: 174487.5
... B382: GRP manhole Dia 1500 mm D=6.5 m W Cover | C382: Ea | D382: 10650
B383: GRP manhole Dia 1500 mm D=7.0 m W Cover | C383: Ea | D383: =D382+950 -> 11600
B384: GRP manhole Dia 1800 mm D=2.0 m W Cover | C384: Ea | D384: 5085
B385: GRP manhole Dia 1800 mm D=2.5 m W Cover | C385: Ea | D385: 5895
B386: GRP manhole Dia 1800 mm D=3.0 m W Cover | C386: Ea | D386: 6705
B387: GRP manhole Dia 1800 mm D=3.5 m W Cover | C387: Ea | D387: 7515
B388: GRP manhole Dia 1800 mm D=4.0 m W Cover | C388: Ea | D388: 8500
B389: GRP manhole Dia 1800 mm D=4.5 m W Cover | C389: Ea | D389: 9450
B390: GRP manhole Dia 1800 mm D=5.0 m W Cover | C390: Ea | D390: 10500
...

Sheet Level 3
C1: PAY ITEM No. (Refer Attach "D" Article 2-03) | D1: DESCRIPTION OF ITEMS | E1: Budget Amount | H1: Subcontractor | I1: Material | J1: Manpower | K1: Machinery
A2: ENVIRONMENTAL WORKS | B2: STORM DRAINAGE NETWORK | D2: Direct Budget | E2: =Budget!T35 -> 1.2100023e+08
A3: ENVIRONMENTAL WORKS | B3: STORM DRAINAGE NETWORK | D3: Material | E3: =+Budget!AF35 -> 219500
A4: ENVIRONMENTAL WORKS | B4: STORM DRAINAGE NETWORK | C4: 15.4 | D4: Manpower | E4: =+Budget!AG35 -> 219500
A5: ENVIRONMENTAL WORKS | B5: STORM DRAINAGE NETWORK | C5: 15.4.1 | D5: Machinery | E5: =+Budget!AE35 -> 219500 | H5: =SUMIF(#REF!,$H$1,#REF!) -> #REF! | I5: =SUMIF(#REF!,$I$1,#REF!) -> #REF! | J5: =SUMIF(#REF!,$J$1,#REF!) -> #REF! | K5: =SUMIF(#REF!,$K$1,#REF!) -> #REF! | L5: =+#REF!-H5-I5-J5-K5 -> #REF!
A6: ENVIRONMENTAL WORKS | B6: STORM DRAINAGE NETWORK | D6: Subcontractor | E6: =+Budget!AH35 -> 219500
H7: 1658389.6 | I7: 16442314 | J7: 2825018.1 | K7: 5795428.4
A8: ENVIRONMENTAL WORKS | B8: STORM DRAINAGE NETWORK | D8: Indirect Budget | E8: =Budget!T16 -> 37202527
A10: ENVIRONMENTAL WORKS | B10: STORM DRAINAGE NETWORK | D10: Total Project Budget | E10: =+E2+E8 -> 1.5820276e+08

Sheet Summary
C1: overall BUDGET Summary
B2: PROJECT NAME: | C2: MODON 3rd Industrial City Phase 1D – Part 2 – Dammam | D2: REV. DATE.: | E2: 45874
B3: SITE LOCATION: | C3: Eastern Region | D3: REV. NO.: | E3: 0
B4: START DATE: | C4: 45778 | D4: PROJECT CODE: | E4: S1-CNS-EP-MOD-2025.3
B5: DURATION: | C5: 16 MTH | D5: CONTRACT PRICE : | E5: 2.3377608e+08
B6: FINISH DATE: | C6: 46538 | D6: BU Number: | E6: 0
B7: REV. FINISH DATE: | C7: 0
B11: No. | C11: Description | D11: Budget | E11: Remark
B12: 1 | C12: Direct Cost | D12: =Budget!I35 -> 1.2100023e+08
B13: =B12+1 -> 2 | C13: Indirect Cost | D13: =Budget!I16 -> 37202527
B14: =B13+1 -> 3 | C14: Contingency Reserve | D14: =E14*E5 -> 23377608 | E14: 0.1
C15: Total Amount | D15: =SUM(D12:D14) -> 1.8158037e+08
C17: Items | D17: Amount | E17: %
B18: A | C18: Contract Price | D18: =E5 -> 2.3377608e+08 | E18: =IFERROR(D18/$E$5,0) -> 1
B19: B | C19: Direct Cost | D19: =-D12 -> -1.2100023e+08 | E19: =-D19/$D$18 -> 0.51759031
B20: C | C20: Indirect Cost | D20: =-D13 -> -37202527 | E20: =-D20/$D$18 -> 0.15913744
B21: D | C21: Contingency Reserve | D21: =-D14 -> -23377608 | E21: =-D21/$D$18 -> 0.1
B22: E= (B+C+D) | C22: Sub-Total | D22: =SUM(D19:D21) -> -1.8158037e+08 | E22: =-D22/$D$18 -> 0.77672775
B23: F=(A+E) | C23: Gross Margin | D23: =D18+D22 -> 52195710 | E23: =D23/$E$5 -> 0.22327225
B24: G | C24: Advance Payment Fees | D24: =-E5*10%*0.75%*2*0.5 -> -175332.06 | E24: =-D24/E5 -> 0.00075
B25: H | C25: Performance Bond Fees | D25: -70017 | E25: =-D25/E5 -> 0.00029950456
B26: I | C26: LC Fees | D26: 0 | E26: =-D26/E5 -> 0
B27: J | C27: CAR Insurance | D27: -338506.86 | E27: =-D27/E5 -> 0.0014479962
B28: K | C28: Management Reserve | D28: =-(E28*E5) -> -1168880.4 | E28: 0.005
B29: L | C29: General and Administrative Expenses (G&A) | D29: =-E29*E5 -> -11688804 | E29: 0.05
B30: K=(F+G+H+I+J+K+L) | C30: Net Profit Margin | D30: =D23+D24+D25+D26+D27+D28+D29 -> 38754170 | E30: =D30/$E$5 -> 0.16577475
